wpcv/__init__.py
wpcv/clitools/__init__.py
wpcv/clitools/cli.py
wpcv/clitools/img.py
wpcv/modellib/__init__.py
wpcv/modellib/resnet/__init__.py
wpcv/modellib/resnet/resnets.py
wpcv/models/__init__.py
wpcv/models/quadnet/__init__.py
wpcv/models/quadnet/loss.py
wpcv/models/quadnet/network.py
wpcv/models/quadnet/quadnet/__init__.py
wpcv/models/quadnet/quadnet/loss.py
wpcv/models/quadnet/quadnet/quadnet.py
wpcv/models/quadnet/quadnet/efficientdet/__init__.py
wpcv/models/quadnet/quadnet/efficientdet/config.py
wpcv/models/quadnet/quadnet/efficientdet/dataset.py
wpcv/models/quadnet/quadnet/efficientdet/loss.py
wpcv/models/quadnet/quadnet/efficientdet/model.py
wpcv/models/quadnet/quadnet/efficientdet/utils.py
wpcv/models/quadnet/quadnet/efficientnet/__init__.py
wpcv/models/quadnet/quadnet/efficientnet/model.py
wpcv/models/quadnet/quadnet/efficientnet/utils.py
wpcv/models/quadnet/quadnet/efficientnet/utils_extra.py
wpcv/models/resnet/__init__.py
wpcv/models/resnet/predict.py
wpcv/models/resnet/test.py
wpcv/models/resnet/train.py
wpcv/models/resnet/val.py
wpcv/models/resnet_v2/__init__.py
wpcv/models/resnet_v2/model.py
wpcv/models/resnet_v2/train.py
wpcv/plp/__init__.py
wpcv/plp/base.py
wpcv/plp/utils.py
wpcv/plp/data/__init__.py
wpcv/plp/data/data.py
wpcv/plp/data/quadnet.py
wpcv/plp/trainers/__init__.py
wpcv/plp/trainers/classifiers.py
wpcv/plp/trainers/keypoint_detector.py
wpcv/scripts/__init__.py
wpcv/scripts/pil_adjust_hue_saturation.py
wpcv/scripts/pil_emboss_numpy.py
wpcv/scripts/pil_image_trans_ops.py
wpcv/scripts/pil_mesh.py
wpcv/scripts/python_image_noise.py
wpcv/scripts/trainers/__init__.py
wpcv/scripts/trainers/quadnet_trainer.py
wpcv/scripts/trainers/resnet.py
wpcv/utils/__init__.py
wpcv/utils/boxutils.py
wpcv/utils/dataset.py
wpcv/utils/imutils.py
wpcv/utils/data_aug/__init__.py
wpcv/utils/data_aug/base.py
wpcv/utils/data_aug/functional.py
wpcv/utils/data_aug/img_aug.py
wpcv/utils/data_aug/det_aug/__init__.py
wpcv/utils/data_aug/det_aug/_demo.py
wpcv-0.0.4.9.dist-info/LICENSE
wpcv-0.0.4.9.dist-info/METADATA
wpcv-0.0.4.9.dist-info/WHEEL
wpcv-0.0.4.9.dist-info/entry_points.txt
wpcv-0.0.4.9.dist-info/top_level.txt
wpcv-0.0.4.9.dist-info/RECORD
