Metadata-Version: 2.1
Name: wpcv
Version: 0.0.4.9
Summary: CV Devkit of Wang Pei
Home-page: https://github.com/Peiiii/wpcv
Author: Wang Pei
Author-email: 1535376447@qq.com
License: UNKNOWN
Platform: UNKNOWN
Classifier: Programming Language :: Python :: 3
Classifier: License :: OSI Approved :: MIT License
Classifier: Operating System :: OS Independent
Requires-Python: >=3.0
